typed_settings/__init__.py
typed_settings/_compat.py
typed_settings/_core.py
typed_settings/_file_utils.py
typed_settings/_onepassword.py
typed_settings/argparse_utils.py
typed_settings/attrs.py
typed_settings/cli_argparse.py
typed_settings/cli_click.py
typed_settings/cli_utils.py
typed_settings/click_utils.py
typed_settings/cls_attrs.py
typed_settings/cls_utils.py
typed_settings/constants.py
typed_settings/converters.py
typed_settings/dict_utils.py
typed_settings/exceptions.py
typed_settings/loaders.py
typed_settings/mypy.py
typed_settings/processors.py
typed_settings/py.typed
typed_settings/types.py
typed_settings-25.1.0.dist-info/METADATA
typed_settings-25.1.0.dist-info/WHEEL
typed_settings-25.1.0.dist-info/licenses/LICENSE
typed_settings-25.1.0.dist-info/RECORD
